{
  "namespaces": [
    "public"
  ],
  "name": "public",
  "tables": [
    {
      "columns": {
        "id": {
          "name": "id",
          "type": "serial",
          "unsigned": true,
          "autoincrement": true,
          "primary": true,
          "nullable": false,
          "mappedType": "integer"
        },
        "created_at": {
          "name": "created_at",
          "type": "timestamptz",
          "unsigned": false,
          "autoincrement": false,
          "primary": false,
          "nullable": false,
          "length": 6,
          "mappedType": "datetime"
        },
        "updated_at": {
          "name": "updated_at",
          "type": "timestamptz",
          "unsigned": false,
          "autoincrement": false,
          "primary": false,
          "nullable": false,
          "length": 6,
          "mappedType": "datetime"
        },
        "name": {
          "name": "name",
          "type": "text",
          "unsigned": false,
          "autoincrement": false,
          "primary": false,
          "nullable": false,
          "mappedType": "text"
        }
      },
      "name": "groups",
      "schema": "public",
      "indexes": [
        {
          "columnNames": [
            "name"
          ],
          "composite": false,
          "keyName": "groups_name_index",
          "constraint": false,
          "primary": false,
          "unique": false
        },
        {
          "keyName": "groups_pkey",
          "columnNames": [
            "id"
          ],
          "composite": false,
          "constraint": true,
          "primary": true,
          "unique": true
        }
      ],
      "checks": [],
      "foreignKeys": {},
      "nativeEnums": {}
    },
    {
      "columns": {
        "id": {
          "name": "id",
          "type": "serial",
          "unsigned": true,
          "autoincrement": true,
          "primary": true,
          "nullable": false,
          "mappedType": "integer"
        },
        "created_at": {
          "name": "created_at",
          "type": "timestamptz",
          "unsigned": false,
          "autoincrement": false,
          "primary": false,
          "nullable": false,
          "length": 6,
          "mappedType": "datetime"
        },
        "updated_at": {
          "name": "updated_at",
          "type": "timestamptz",
          "unsigned": false,
          "autoincrement": false,
          "primary": false,
          "nullable": false,
          "length": 6,
          "mappedType": "datetime"
        },
        "title": {
          "name": "title",
          "type": "text",
          "unsigned": false,
          "autoincrement": false,
          "primary": false,
          "nullable": false,
          "mappedType": "text"
        },
        "content": {
          "name": "content",
          "type": "text",
          "unsigned": false,
          "autoincrement": false,
          "primary": false,
          "nullable": true,
          "mappedType": "text"
        }
      },
      "name": "todos",
      "schema": "public",
      "indexes": [
        {
          "columnNames": [
            "title"
          ],
          "composite": false,
          "keyName": "todos_title_index",
          "constraint": false,
          "primary": false,
          "unique": false
        },
        {
          "keyName": "todos_pkey",
          "columnNames": [
            "id"
          ],
          "composite": false,
          "constraint": true,
          "primary": true,
          "unique": true
        }
      ],
      "checks": [],
      "foreignKeys": {},
      "nativeEnums": {}
    },
    {
      "columns": {
        "id": {
          "name": "id",
          "type": "serial",
          "unsigned": true,
          "autoincrement": true,
          "primary": true,
          "nullable": false,
          "mappedType": "integer"
        },
        "created_at": {
          "name": "created_at",
          "type": "timestamptz",
          "unsigned": false,
          "autoincrement": false,
          "primary": false,
          "nullable": false,
          "length": 6,
          "mappedType": "datetime"
        },
        "updated_at": {
          "name": "updated_at",
          "type": "timestamptz",
          "unsigned": false,
          "autoincrement": false,
          "primary": false,
          "nullable": false,
          "length": 6,
          "mappedType": "datetime"
        },
        "name": {
          "name": "name",
          "type": "text",
          "unsigned": false,
          "autoincrement": false,
          "primary": false,
          "nullable": false,
          "mappedType": "text"
        }
      },
      "name": "users",
      "schema": "public",
      "indexes": [
        {
          "columnNames": [
            "name"
          ],
          "composite": false,
          "keyName": "users_name_index",
          "constraint": false,
          "primary": false,
          "unique": false
        },
        {
          "keyName": "users_pkey",
          "columnNames": [
            "id"
          ],
          "composite": false,
          "constraint": true,
          "primary": true,
          "unique": true
        }
      ],
      "checks": [],
      "foreignKeys": {},
      "nativeEnums": {}
    },
    {
      "columns": {
        "group_id": {
          "name": "group_id",
          "type": "int",
          "unsigned": false,
          "autoincrement": false,
          "primary": false,
          "nullable": false,
          "mappedType": "integer"
        },
        "user_id": {
          "name": "user_id",
          "type": "int",
          "unsigned": false,
          "autoincrement": false,
          "primary": false,
          "nullable": false,
          "mappedType": "integer"
        }
      },
      "name": "group_user",
      "schema": "public",
      "indexes": [
        {
          "keyName": "group_user_pkey",
          "columnNames": [
            "group_id",
            "user_id"
          ],
          "composite": true,
          "constraint": true,
          "primary": true,
          "unique": true
        }
      ],
      "checks": [],
      "foreignKeys": {
        "group_user_group_id_foreign": {
          "constraintName": "group_user_group_id_foreign",
          "columnNames": [
            "group_id"
          ],
          "localTableName": "public.group_user",
          "referencedColumnNames": [
            "id"
          ],
          "referencedTableName": "public.groups",
          "deleteRule": "cascade",
          "updateRule": "cascade"
        },
        "group_user_user_id_foreign": {
          "constraintName": "group_user_user_id_foreign",
          "columnNames": [
            "user_id"
          ],
          "localTableName": "public.group_user",
          "referencedColumnNames": [
            "id"
          ],
          "referencedTableName": "public.users",
          "deleteRule": "cascade",
          "updateRule": "cascade"
        }
      },
      "nativeEnums": {}
    }
  ],
  "nativeEnums": {}
}
